ptolemy/__init__.py
ptolemy/raster.py
ptolemy_iamc-0.4.dist-info/LICENSE
ptolemy_iamc-0.4.dist-info/METADATA
ptolemy_iamc-0.4.dist-info/WHEEL
ptolemy_iamc-0.4.dist-info/top_level.txt
ptolemy_iamc-0.4.dist-info/RECORD
